{"total_rows":24,"offset":0,"rows":[
{"id":"pmc:10.1371/journal.pbio.0000045","key":"10.1371/journal.pbio.0000045","value":{"2013-7":28,"2013-8":24}},
{"id":"pmc:10.1371/journal.pbio.0030137","key":"10.1371/journal.pbio.0030137","value":{"2013-7":1}},
{"id":"pmc:10.1371/journal.pbio.0040015","key":"10.1371/journal.pbio.0040015","value":{"2013-7":9,"2013-8":10}},
{"id":"pmc:10.1371/journal.pbio.0050254","key":"10.1371/journal.pbio.0050254","value":{"2013-7":78,"2013-8":103}},
{"id":"pmc:10.1371/journal.pbio.0060188","key":"10.1371/journal.pbio.0060188","value":{"2013-7":30,"2013-8":19}},
{"id":"pmc:10.1371/journal.pbio.1000242","key":"10.1371/journal.pbio.1000242","value":{"2013-7":6,"2013-8":3}},
{"id":"pmc:10.1371/journal.pcbi.0010057","key":"10.1371/journal.pcbi.0010057","value":{"2013-7":115,"2013-8":53}},
{"id":"pmc:10.1371/journal.pcbi.0020131","key":"10.1371/journal.pcbi.0020131","value":{"2013-7":6,"2013-8":1}},
{"id":"pmc:10.1371/journal.pcbi.1000204","key":"10.1371/journal.pcbi.1000204","value":{"2013-7":81,"2013-8":74}},
{"id":"pmc:10.1371/journal.pcbi.1002445","key":"10.1371/journal.pcbi.1002445","value":{"2013-7":15,"2013-8":25}},
{"id":"pmc:10.1371/journal.pmed.0020124","key":"10.1371/journal.pmed.0020124","value":{"2013-7":2375,"2013-8":2572}},
{"id":"pmc:10.1371/journal.pmed.0020146","key":"10.1371/journal.pmed.0020146","value":{"2013-7":48,"2013-8":25}},
{"id":"pmc:10.1371/journal.pone.0000443","key":"10.1371/journal.pone.0000443","value":{"2013-7":5,"2013-8":8}},
{"id":"pmc:10.1371/journal.pone.0001636","key":"10.1371/journal.pone.0001636","value":{"2013-7":10,"2013-8":8}},
{"id":"pmc:10.1371/journal.pone.0006872","key":"10.1371/journal.pone.0006872","value":{"2013-7":15,"2013-8":25}},
{"id":"pmc:10.1371/journal.pone.0008776","key":"10.1371/journal.pone.0008776","value":{"2013-7":8,"2013-8":7}},
{"id":"pmc:10.1371/journal.pone.0018657","key":"10.1371/journal.pone.0018657","value":{"2013-7":7,"2013-8":9}},
{"id":"pmc:10.1371/journal.pone.0020094","key":"10.1371/journal.pone.0020094","value":{"2013-7":9,"2013-8":3}},
{"id":"pmc:10.1371/journal.pone.0033288","key":"10.1371/journal.pone.0033288","value":{"2013-7":11,"2013-8":9}},
{"id":"pmc:10.1371/journal.pone.0035869","key":"10.1371/journal.pone.0035869","value":{"2013-7":30,"2013-8":39}},
{"id":"pmc:10.1371/journal.pone.0036240","key":"10.1371/journal.pone.0036240","value":{"2013-7":3,"2013-8":5}},
{"id":"pmc:10.1371/journal.pone.0036790","key":"10.1371/journal.pone.0036790","value":{"2013-7":4,"2013-8":11}},
{"id":"pmc:10.1371/journal.pone.0044271","key":"10.1371/journal.pone.0044271","value":{"2013-7":33,"2013-8":12}},
{"id":"pmc:10.1371/journal.ppat.1000446","key":"10.1371/journal.ppat.1000446","value":{"2013-7":8,"2013-8":7}}
]}
