{
  "search-results": {
    "opensearch:totalResults": "1",
    "opensearch:startIndex": "0",
    "opensearch:itemsPerPage": "1",
    "opensearch:Query": {
      "@role": "request",
      "@searchTerms": "DOI%2810.1371%2Fjournal.pmed.0030442%29",
      "@startPage": "0"
    },
    "link": [
      {
        "@_fa": "true",
        "@ref": "self",
        "@href": "http://api.elsevier.com:80/content/search/index:scopus?start=0&count=25&query=DOI(10.1371/journal.pmed.0030442)&apiKey=13d2f5fc673aca2a725b7db8d18651fa&insttoken=9a2a694bed39b51f25cc0ed5ea5c921b",
        "@type": "application/json"
      },
      {
        "@_fa": "true",
        "@ref": "first",
        "@href": "http://api.elsevier.com:80/content/search/index:scopus?start=0&count=25&query=DOI(10.1371/journal.pmed.0030442)&apiKey=13d2f5fc673aca2a725b7db8d18651fa&insttoken=9a2a694bed39b51f25cc0ed5ea5c921b",
        "@type": "application/json"
      }
    ],
    "entry": [
      {
        "@_fa": "true",
        "link": [
          {
            "@_fa": "true",
            "@ref": "self",
            "@href": "http://api.elsevier.com/content/abstract/scopus_id:33845338724"
          },
          {
            "@_fa": "true",
            "@ref": "scopus",
            "@href": "http://www.scopus.com/inward/record.url?partnerID=HzOxMe3b&scp=33845338724"
          },
          {
            "@_fa": "true",
            "@ref": "scopus-citedby",
            "@href": "http://www.scopus.com/inward/citedby.url?partnerID=HzOxMe3b&scp=33845338724"
          }
        ],
        "prism:url": "http://api.elsevier.com/content/abstract/scopus_id:33845338724",
        "dc:identifier": "SCOPUS_ID:33845338724",
        "eid": "2-s2.0-33845338724",
        "dc:title": "Projections of global mortality and burden of disease from 2002 to 2030",
        "dc:creator": "Mathers, C.D.",
        "prism:publicationName": "PLoS Medicine",
        "prism:issn": "15491277",
        "prism:eIssn": "15491676",
        "prism:volume": "3",
        "prism:issueIdentifier": "11",
        "prism:pageRange": "2011-2030",
        "prism:coverDate": "2006-11-01",
        "prism:coverDisplayDate": "November 2006",
        "prism:doi": "10.1371/journal.pmed.0030442",
        "citedby-count": "1814",
        "affiliation": [
          {
            "@_fa": "true",
            "affilname": "Organisation Mondiale de la Santé",
            "affiliation-city": "Geneve",
            "affiliation-country": "Switzerland"
          }
        ],
        "pubmed-id": "17132052",
        "prism:aggregationType": "Journal",
        "subtype": "ar",
        "subtypeDescription": "Article"
      }
    ]
  }
}